quick/__init__.py
quick/__main__.py
quick/commands/__init__.py
quick/commands/base.py
quick/commands/context.py
quick/commands/gateway.py
quick/commands/mirror.py
quick/commands/streams_app.py
quick/commands/topic.py
quick/config.py
quick/driver.py
quick/exception.py
quick/generate_docs.py
quick/parser.py
quick_client/__init__.py
quick_client/api/__init__.py
quick_client/api/default_api.py
quick_client/api_client.py
quick_client/configuration.py
quick_client/docs/DefaultApi.md
quick_client/exceptions.py
quick_client/models/__init__.py
quick_client/models/application_creation_data.py
quick_client/models/application_creation_data_arguments.py
quick_client/models/error_message.py
quick_client/models/gateway_creation_data.py
quick_client/models/gateway_description.py
quick_client/models/gateway_schema.py
quick_client/models/mirror_creation_data.py
quick_client/models/quick_topic_type.py
quick_client/models/schema_data.py
quick_client/models/topic_creation_data.py
quick_client/models/topic_data.py
quick_client/models/topic_write_type.py
quick_client/rest.py
quick_cli-0.8.0.dist-info/entry_points.txt
quick_cli-0.8.0.dist-info/LICENSE
quick_cli-0.8.0.dist-info/WHEEL
quick_cli-0.8.0.dist-info/METADATA
quick_cli-0.8.0.dist-info/RECORD
