Metadata-Version: 2.1
Name: quick-cli
Version: 0.8.0
Summary: The CLI to control your quick cluster.
Home-page: https://d9p.io/
License: Apache-2.0
Author: d9p
Author-email: contact@d9p.io
Requires-Python: >=3.7,<4.0
Classifier: Environment :: Console
Classifier: Intended Audience :: Information Technology
Classifier: License :: OSI Approved :: Apache Software License
Classifier: Operating System :: OS Independent
Classifier: Programming Language :: Python
Classifier: Programming Language :: Python :: 3
Classifier: Programming Language :: Python :: 3 :: Only
Classifier: Programming Language :: Python :: 3.10
Classifier: Programming Language :: Python :: 3.7
Classifier: Programming Language :: Python :: 3.8
Classifier: Programming Language :: Python :: 3.9
Classifier: Topic :: Software Development
Classifier: Topic :: Software Development :: Libraries
Classifier: Topic :: Software Development :: Libraries :: Application Frameworks
Classifier: Topic :: Software Development :: Libraries :: Python Modules
Classifier: Typing :: Typed
Requires-Dist: PyYAML (>=5.3,<6.0)
Requires-Dist: isodate (>=0.6.0,<0.7.0)
Requires-Dist: python-dateutil (>=2.5.0,<3.0.0)
Requires-Dist: requests (>=2.0.0,<3.0.0)
Requires-Dist: six (>=1.12.0,<2.0.0)
Requires-Dist: urllib3 (>=1.0,<2.0)
Project-URL: Documentation, https://d9p.io/tutorials/
Project-URL: Repository, https://github.com/bakdata/quick-cli
